dify_api_python/__init__.py
dify_api_python/client.py
dify_api_python/sdk.py
dify_api_python-0.1.5.dist-info/LICENSE
dify_api_python-0.1.5.dist-info/METADATA
dify_api_python-0.1.5.dist-info/WHEEL
dify_api_python-0.1.5.dist-info/top_level.txt
dify_api_python-0.1.5.dist-info/RECORD
