Metadata-Version: 2.1
Name: dify-api-python
Version: 0.1.5
Summary: A Python client for the Dify API
Home-page: https://github.com/zlz3907/dify-api-python
Author: zlz3907
Author-email: zlz3907@gmail.com
License: Apache License 2.0
Platform: UNKNOWN
Classifier: Development Status :: 3 - Alpha
Classifier: Intended Audience :: Developers
Classifier: License :: OSI Approved :: Apache Software License
Classifier: Programming Language :: Python :: 3
Classifier: Programming Language :: Python :: 3.7
Classifier: Programming Language :: Python :: 3.8
Classifier: Programming Language :: Python :: 3.9
Classifier: Programming Language :: Python :: 3.10
Requires-Python: >=3.7
License-File: LICENSE
Requires-Dist: requests>=2.25.0
Requires-Dist: sseclient-py>=1.7.2
